IPRemote/__init__.py
IPRemote/__main__.py
IPRemote/application.py
IPRemote/config.py
IPRemote/exceptions.py
IPRemote/interactive.py
IPRemote/key_mappings.py
IPRemote/remote.py
IPRemote/remote_legacy.py
IPRemote/remote_websocket.py
IPRemote/utils.py
IPRemote/wake_on_lan.py
IPRemote/websocket_base.py
IPRemote/remote_encrypted/__init__.py
IPRemote/remote_encrypted/command_encryption.py
IPRemote/remote_encrypted/crypto.py
IPRemote/remote_encrypted/keys.py
IPRemote/remote_encrypted/py3rijndael/__init__.py
IPRemote/remote_encrypted/py3rijndael/constants.py
IPRemote/remote_encrypted/py3rijndael/paddings.py
IPRemote/remote_encrypted/py3rijndael/rijndael.py
IPRemote/upnp/__init__.py
IPRemote/upnp/discover.py
IPRemote/upnp/UPNP_Device/__init__.py
IPRemote/upnp/UPNP_Device/__main__.py
IPRemote/upnp/UPNP_Device/action.py
IPRemote/upnp/UPNP_Device/data_type.py
IPRemote/upnp/UPNP_Device/discover.py
IPRemote/upnp/UPNP_Device/embedded_device.py
IPRemote/upnp/UPNP_Device/icon.py
IPRemote/upnp/UPNP_Device/instance_singleton.py
IPRemote/upnp/UPNP_Device/listen.py
IPRemote/upnp/UPNP_Device/service.py
IPRemote/upnp/UPNP_Device/upnp_class.py
IPRemote/upnp/UPNP_Device/xmlns.py
IPRemote-0.1.8.dist-info/LICENSE
IPRemote-0.1.8.dist-info/METADATA
IPRemote-0.1.8.dist-info/WHEEL
IPRemote-0.1.8.dist-info/entry_points.txt
IPRemote-0.1.8.dist-info/top_level.txt
IPRemote-0.1.8.dist-info/RECORD
