Metadata-Version: 2.1
Name: IPRemote
Version: 0.1.8
Summary: UNKNOWN
Home-page: https://github.com/MikishVaughn/IPRemote
Author: Michael Vaughn
Author-email: mikish.vaughn@gmail.com
License: MIT
Platform: UNKNOWN
Classifier: Development Status :: 4 - Beta
Classifier: Environment :: Console
Classifier: License :: OSI Approved :: MIT License
Classifier: Programming Language :: Python :: 3
Classifier: Topic :: Home Automation
Requires-Dist: websocket-client
Requires-Dist: requests
Requires-Dist: lxml
Requires-Dist: six
Requires-Dist: ifaddr
Requires-Dist: pycryptodome
